jrpypytorch/__init__.py
jrpypytorch-0.1.0.dist-info/WHEEL
jrpypytorch-0.1.0.dist-info/METADATA
jrpypytorch-0.1.0.dist-info/RECORD
