Metadata-Version: 2.1
Name: jrpypytorch
Version: 0.1.0
Summary: 
Home-page: UNKNOWN
License: UNKOWN
Author: Jamie
Author-email: jamie@jumpingrivers.com
Requires-Python: *
Classifier: Programming Language :: Python :: 2
Classifier: Programming Language :: Python :: 2.7
Classifier: Programming Language :: Python :: 3
Classifier: Programming Language :: Python :: 3.4
Classifier: Programming Language :: Python :: 3.5
Classifier: Programming Language :: Python :: 3.6
Classifier: Programming Language :: Python :: 3.7
Requires-Dist: matplotlib (>=3.0,<4.0)
Requires-Dist: numpy (>=1.15,<2.0)
Requires-Dist: sklearn (>=0.0.0,<0.0.1)
Requires-Dist: torch (>=1.0,<2.0)
Requires-Dist: torchvision (>=0.2.1,<0.3.0)
